{"nodes": [{"id": "c_users_chris_inmobiliariaauto_backend_modelos_base_py", "label": "base.py", "file_type": "code", "source_file": "backend/modelos/base.py", "source_location": "L1"}, {"id": "c_users_chris_inmobiliariaauto_backend_modelos_base_modelobase", "label": "ModeloBase", "file_type": "code", "source_file": "backend/modelos/base.py", "source_location": "L6", "_callable": true}, {"id": "basemodel", "label": "BaseModel", "file_type": "code", "source_file": "", "source_location": "", "origin_file": "C:\\Users\\chris\\inmobiliariaAuto\\backend\\modelos\\base.py"}, {"id": "c_users_chris_inmobiliariaauto_backend_modelos_base_rationale_1", "label": "Modelo base Pydantic v2 con validaci\u00f3n estricta.", "file_type": "rationale", "source_file": "backend/modelos/base.py", "source_location": "L1"}, {"id": "c_users_chris_inmobiliariaauto_backend_modelos_base_rationale_7", "label": "Base de todos los modelos.      `extra=\"forbid\"`: cualquier campo no declarado e", "file_type": "rationale", "source_file": "backend/modelos/base.py", "source_location": "L7"}], "edges": [{"source": "c_users_chris_inmobiliariaauto_backend_modelos_base_py", "target": "pydantic", "relation": "imports_from", "context": "import", "confidence": "EXTRACTED", "source_file": "backend/modelos/base.py", "source_location": "L3", "weight": 1.0}, {"source": "c_users_chris_inmobiliariaauto_backend_modelos_base_py", "target": "c_users_chris_inmobiliariaauto_backend_modelos_base_modelobase", "relation": "contains", "confidence": "EXTRACTED", "source_file": "backend/modelos/base.py", "source_location": "L6", "weight": 1.0}, {"source": "c_users_chris_inmobiliariaauto_backend_modelos_base_modelobase", "target": "basemodel", "relation": "inherits", "confidence": "EXTRACTED", "source_file": "backend/modelos/base.py", "source_location": "L6", "weight": 1.0}, {"source": "c_users_chris_inmobiliariaauto_backend_modelos_base_rationale_1", "target": "c_users_chris_inmobiliariaauto_backend_modelos_base_py", "relation": "rationale_for", "confidence": "EXTRACTED", "source_file": "backend/modelos/base.py", "source_location": "L1", "weight": 1.0}, {"source": "c_users_chris_inmobiliariaauto_backend_modelos_base_rationale_7", "target": "c_users_chris_inmobiliariaauto_backend_modelos_base_modelobase", "relation": "rationale_for", "confidence": "EXTRACTED", "source_file": "backend/modelos/base.py", "source_location": "L7", "weight": 1.0}], "raw_calls": []}